main.py
setup.py
raylink.egg-info/PKG-INFO
raylink.egg-info/SOURCES.txt
raylink.egg-info/dependency_links.txt
raylink.egg-info/requires.txt
raylink.egg-info/top_level.txt